cryptomite/__init__.py
cryptomite/_cryptomite.cp39-win_amd64.pyd
cryptomite/circulant.py
cryptomite/dodis.py
cryptomite/raz.py
cryptomite/toeplitz.py
cryptomite/trevisan.py
cryptomite/utils.py
cryptomite-0.3.0.dist-info/METADATA
cryptomite-0.3.0.dist-info/WHEEL
cryptomite-0.3.0.dist-info/top_level.txt
cryptomite-0.3.0.dist-info/RECORD
