Metadata-Version: 2.4
Name: cryptomite
Version: 0.3.0
Summary: An awesome extractor library
Author: Cambridge Quantum
Author-email: qcrypto@cambridgequantum.com
Keywords: quantum,quantum computing
Classifier: Intended Audience :: Developers
Classifier: Intended Audience :: Science/Research
Classifier: Operating System :: OS Independent
Classifier: Programming Language :: Python :: 3
Classifier: Programming Language :: Python :: 3.8
Classifier: Programming Language :: Python :: 3.9
Classifier: Programming Language :: Python :: 3.10
Classifier: Topic :: Scientific/Engineering
Requires-Python: >=3.8
